[
 {
   "id": 2001,
   "Fabricante": "RAM",
   "Marca": "TEAMGROUP",
   "Modelo": "T-FORCE VULCAN Z 4GB, DDR4 3000MHZ GRAY",
   "PrecioME": "$31,00",
   "PrecioMN": "S/.114,08",
   "Almacen": "6"
 },
 {
   "id": 2002,
   "Fabricante": "RAM",
   "Marca": "KINGSTON",
   "Modelo": "HYPERX FURY DDR4 4GB/2666 NEGRO",
   "PrecioME": "$33,00",
   "PrecioMN": "S/.121,44",
   "Almacen": "CONSULTAR STOCK"
 },
 {
   "id": 2003,
   "Fabricante": "RAM",
   "Marca": "HP",
   "Modelo": "MEMORIA RAM HP V6 SERIES 8GB DDR4 2666MHZ",
   "PrecioME": "$43,00",
   "PrecioMN": "S/.158,24",
   "Almacen": "5"
 },
 {
   "id": 2004,
   "Fabricante": "RAM",
   "Marca": "HYPERX",
   "Modelo": "HYPERX FURY DDR4 8GB/2666 NEGRO",
   "PrecioME": "$43,00",
   "PrecioMN": "S/.158,24",
   "Almacen": "AGOTADO"
 },
 {
   "id": 2005,
   "Fabricante": "RAM",
   "Marca": "TEAMGROUP",
   "Modelo": "Memoria T-Force Vulcan Z, 8GB, DDR4, 2666 MHz, CL-16",
   "PrecioME": "$45,00",
   "PrecioMN": "S/.165,60",
   "Almacen": "2"
 },
 {
   "id": 2006,
   "Fabricante": "RAM",
   "Marca": "GEIL",
   "Modelo": "MEMORIA RAM GEIL ORION, 8GB, DDR4, 3000 MHZ",
   "PrecioME": "$46,50",
   "PrecioMN": "S/.171,12",
   "Almacen": "9"
 },
 {
   "id": 2007,
   "Fabricante": "RAM",
   "Marca": "GEIL",
   "Modelo": "MEMORIA RAM GEIL ORION, 8GB, DDR4, 3200 MHZ",
   "PrecioME": "$48,00",
   "PrecioMN": "S/.176,64",
   "Almacen": "4"
 },
 {
   "id": 2008,
   "Fabricante": "RAM",
   "Marca": "GEIL",
   "Modelo": "MEMORIA RAM GEIL EVO POTENZA 8GB 3200MHZ",
   "PrecioME": "$48,00",
   "PrecioMN": "S/.176,64",
   "Almacen": "CONSULTAR STOCK"
 },
 {
   "id": 2009,
   "Fabricante": "RAM",
   "Marca": "TEAMGROUP",
   "Modelo": "Memoria T-Force Vulcan Z, 8GB, DDR4, 3200 MHz, CL-16",
   "PrecioME": "$49,00",
   "PrecioMN": "S/.180,32",
   "Almacen": "4"
 },
 {
   "id": 2010,
   "Fabricante": "RAM",
   "Marca": "TEAMGROUP",
   "Modelo": "MEMORIA SODIMM T-FORCE VULCAN 8GB 3200MHZ DDR4 | RED",
   "PrecioME": "$49,00",
   "PrecioMN": "S/.180,32",
   "Almacen": "9"
 },
 {
   "id": 2011,
   "Fabricante": "RAM",
   "Marca": "KINGSTON",
   "Modelo": "MEMORIA DDR4 KINGSTON 8GB 3200MHZ BLACK CL16",
   "PrecioME": "$49,00",
   "PrecioMN": "S/.180,32",
   "Almacen": "15"
 },
 {
   "id": 2012,
   "Fabricante": "RAM",
   "Marca": "HP",
   "Modelo": "MEMORIA HP V8SERIES 8GB 3200",
   "PrecioME": "$49,00",
   "PrecioMN": "S/.180,32",
   "Almacen": "AGOTADO"
 },
 {
   "id": 2013,
   "Fabricante": "RAM",
   "Marca": "HYPERX",
   "Modelo": "MEM 8G HYPERX 3200GHZ DDR4",
   "PrecioME": "$53,50",
   "PrecioMN": "S/.196,88",
   "Almacen": "5"
 },
 {
   "id": 2014,
   "Fabricante": "RAM",
   "Marca": "TEAMGROUP",
   "Modelo": "MEM. RAM TEAMGROUP T-FORCE DELTA DDR4 8GB/3200 NEGRO LED- RGB",
   "PrecioME": "$58,00",
   "PrecioMN": "S/.213,44",
   "Almacen": "21"
 },
 {
   "id": 2015,
   "Fabricante": "RAM",
   "Marca": "GEIL",
   "Modelo": "MEMORIA RAM GEIL SUPER LUCE RGB 8GB DDR4 3200MHZ",
   "PrecioME": "$58,00",
   "PrecioMN": "S/.213,44",
   "Almacen": "3"
 },
 {
   "id": 2016,
   "Fabricante": "RAM",
   "Marca": "HYPERX",
   "Modelo": "MEM. RAM HYPERX PREDATOR RGB 8GB DDR4 3200 MHZ",
   "PrecioME": "$58,00",
   "PrecioMN": "S/.213,44",
   "Almacen": "AGOTADO"
 },
 {
   "id": 2017,
   "Fabricante": "RAM",
   "Marca": "TEAMGROUP",
   "Modelo": "RAM T-FORCE VULCAN Z 16GB, DDR4 3200MHZ",
   "PrecioME": "$79,00",
   "PrecioMN": "S/.290,72",
   "Almacen": "7"
 },
 {
   "id": 2018,
   "Fabricante": "RAM",
   "Marca": "HYPERX",
   "Modelo": "MEMORIA RAM KINGSTON HYPERX FURY 16GB DDR4 2666MHZ",
   "PrecioME": "$86,00",
   "PrecioMN": "S/.316,48",
   "Almacen": "1"
 },
 {
   "id": 2019,
   "Fabricante": "RAM",
   "Marca": "TEAMGROUP",
   "Modelo": "RAM DDR4 T-FORCE DELTA RGB 16GB 3200MHZ BLACK",
   "PrecioME": "$89,00",
   "PrecioMN": "S/.327,52",
   "Almacen": "3"
 },
 {
   "id": 2020,
   "Fabricante": "RAM",
   "Marca": "CORSAIR",
   "Modelo": "MEMORIA CORSAIR DDR4 16GB 3200MHZ VENGEANCE LPX",
   "PrecioME": "$89,00",
   "PrecioMN": "S/.327,52",
   "Almacen": "CONSULTAR STOCK"
 },
 {
   "id": 2021,
   "Fabricante": "RAM",
   "Marca": "HYPERX",
   "Modelo": "RAM KINGSTON HYPERX FURY 16GB DDR4 3200MHZ",
   "PrecioME": "$95,00",
   "PrecioMN": "S/.349,60",
   "Almacen": "7"
 },
 {
   "id": 2022,
   "Fabricante": "RAM",
   "Marca": "TEAMGROUP",
   "Modelo": "MEMORIA T-FORCE VULCAN Z, 16GB, DDR4, 2666 MHZ",
   "PrecioME": "$95,00",
   "PrecioMN": "S/.349,60",
   "Almacen": "3"
 },
 {
   "id": 2023,
   "Fabricante": "RAM",
   "Marca": "TEAMGROUP",
   "Modelo": "MEMORIA T-FORCE DELTA RGB, 16GB, DDR4, 3000 MHZ, CL-16, 1.35V",
   "PrecioME": "$99,00",
   "PrecioMN": "S/.364,32",
   "Almacen": "CONSULTAR STOCK"
 },
 {
   "id": 2024,
   "Fabricante": "RAM",
   "Marca": "TEAMGROUP",
   "Modelo": "RAM DDR4 T-FORCE DELTA RGB 2X8GB 3200MHZ BLACK",
   "PrecioME": "$119,00",
   "PrecioMN": "S/.437,92",
   "Almacen": "3"
 },
 {
   "id": 2025,
   "Fabricante": "RAM",
   "Marca": "TEAMGROUP",
   "Modelo": "RAM 16 GB (2*8)T-FORCE XCALIBUR RGB DDR4 3600MHZ",
   "PrecioME": "$119,00",
   "PrecioMN": "S/.437,92",
   "Almacen": "41"
 },
 {
   "id": 2026,
   "Fabricante": "RAM",
   "Marca": "TEAMGROUP",
   "Modelo": "RAM DDR4 T-FORCE NIGHT HAWK RGB 16GB 3600MHZ",
   "PrecioME": "$119,00",
   "PrecioMN": "S/.437,92",
   "Almacen": "AGOTADO"
 },
 {
   "id": 2027,
   "Fabricante": "RAM",
   "Marca": "TEAMGROUP",
   "Modelo": "RAM DDR4 T-FORCE DELTA RGB 2X8GB 3200MHZ WHITE",
   "PrecioME": "$125,00",
   "PrecioMN": "S/.460,00",
   "Almacen": "AGOTADO"
 },
 {
   "id": 2028,
   "Fabricante": "RAM",
   "Marca": "TEAMGROUP",
   "Modelo": "RAM DDR4 T-FORCE DARK Z 32GB 3200MHZ RED",
   "PrecioME": "$139,00",
   "PrecioMN": "S/.511,52",
   "Almacen": "AGOTADO"
 },
 {
   "id": 2029,
   "Fabricante": "RAM",
   "Marca": "HYPERX",
   "Modelo": "MEMORIA 8GB DDR4 HYPERX PREDATOR BLACK RGB BUS 3600MHZ",
   "PrecioME": "$69,00",
   "PrecioMN": "S/.253,92",
   "Almacen": "3"
 },
 {
   "id": 2030,
   "Fabricante": "RAM",
   "Marca": "TEAMGROUP",
   "Modelo": "MEMORIA 32GB DDR4 T-FORCE DELTA RGB 3200MHZ",
   "PrecioME": "$169,00",
   "PrecioMN": "S/.621,92",
   "Almacen": "5"
 },
 {
   "id": 2031,
   "Fabricante": "RAM",
   "Marca": "KINGSTON",
   "Modelo": "Memoria Kingston HyperX Fury 16GB DDR4, 3200 MHz",
   "PrecioME": "$99,00",
   "PrecioMN": "S/.364,32",
   "Almacen": "CONSULTAR STOCK"
 },
 {
   "id": 2032,
   "Fabricante": "RAM",
   "Marca": "TEAMGROUP",
   "Modelo": "MEM. RAM TEAM GROUP T-FORCE XTREEM ARGB, 16GB KIT (8GB x2) DDR4 3600 MHZ",
   "PrecioME": "$189,00",
   "PrecioMN": "S/.695,52",
   "Almacen": "7"
 }
]